{"sections":{"1662177748276ef774":{"type":"slideshow","blocks":{"1662177748718c4477-0":{"type":"image","settings":{"image":"shopify:\/\/shop_images\/Group_32_1_56a8f414-7671-4cf0-8428-67cfc8d2294c.png","mobile_image":"shopify:\/\/shop_images\/Group_32_252416a6-1b45-4eeb-b336-e4997c3c24d0.png","apply_overlay":false,"content_position":"middleCenter","subheading":"","title":"Contact us","button_1_text":"","button_1_link":"","button_2_text":"","button_2_link":""}}},"block_order":["1662177748718c4477-0"],"settings":{"show_fullscreen":false,"show_arrow":false,"autoplay":true,"right-image-link":"","cycle_speed":5,"text_color":"#ffffff","button_color":"#363636","button_background":"#ffffff"}},"main":{"type":"main-contact","disabled":true,"settings":{}},"1662190570b1c24fe5":{"type":"contactdetail","blocks":{"205d1a01-9be9-480d-9284-f59014fe0fcb":{"type":"block","settings":{"textbox":"Address","kome1":"BIORESTORE AB","komeurl1":"","kome2":"Metropole C\/O Medborgarplatsen","komeurl2":"","kome3":"118 72 Stockholm","komeurl3":"","kome4":"Sweden","komeurl4":"","kome5":"","komeurl5":""}},"03afce4b-16c2-4c75-9e43-3e08f5fcd580":{"type":"block","settings":{"textbox":"Email us","kome1":"hello@bio-restore.com","komeurl1":"#","kome2":"","komeurl2":"#","kome3":"","komeurl3":"","kome4":"","komeurl4":"","kome5":"","komeurl5":""}},"54c61190-b72c-4c13-91a5-2be9494788bd":{"type":"block","disabled":true,"settings":{"textbox":"Call us","kome1":"+00 000 000 000","komeurl1":"#","kome2":"+00 000 000 000","komeurl2":"#","kome3":"","komeurl3":"","kome4":"","komeurl4":"","kome5":"","komeurl5":""}},"e3b8502b-50da-47bd-98df-544f371a6be8":{"type":"block","settings":{"textbox":"Follow us","kome1":"Facebook","komeurl1":"https:\/\/www.facebook.com\/Biorestoreglobal","kome2":"Twitter","komeurl2":"https:\/\/twitter.com\/bio_RESTORE","kome3":"Youtube","komeurl3":"https:\/\/www.youtube.com\/channel\/UCaRRQNMDbmur1FuRyAB_sCQ\/featured","kome4":"Instagram","komeurl4":"https:\/\/www.instagram.com\/biorestoreglobal\/","kome5":"Linkedin","komeurl5":"https:\/\/www.linkedin.com\/company\/biorestoreab\/"}},"4077c61a-2586-413c-80ae-ec844e55a2d5":{"type":"block","disabled":true,"settings":{"textbox":"","kome1":"","komeurl1":"","kome2":"","komeurl2":"","kome3":"","komeurl3":"","kome4":"","komeurl4":"","kome5":"","komeurl5":""}}},"block_order":["205d1a01-9be9-480d-9284-f59014fe0fcb","03afce4b-16c2-4c75-9e43-3e08f5fcd580","54c61190-b72c-4c13-91a5-2be9494788bd","e3b8502b-50da-47bd-98df-544f371a6be8","4077c61a-2586-413c-80ae-ec844e55a2d5"],"settings":{"SAMPLEfe":""}},"16621908355125fe02":{"type":"ProductContact","blocks":{"6d9b7765-3c0e-4d75-bf4b-bb0768af8ff2":{"type":"block","settings":{"kome":"SHOP NOW!","komurl":"https:\/\/www.bio-restore.com\/products"}},"1cd59c42-cd3e-4f82-90ad-e688290fa720":{"type":"block","settings":{"kome":"STOCKISTS COMING SOON","komurl":"shopify:\/\/pages\/stockists"}}},"block_order":["6d9b7765-3c0e-4d75-bf4b-bb0768af8ff2","1cd59c42-cd3e-4f82-90ad-e688290fa720"],"settings":{"prdtitle":"Want our product?"}}},"order":["1662177748276ef774","main","1662190570b1c24fe5","16621908355125fe02"]}